{
    "data": [
        {
            "username": "Tobias",
            "state": "das",
            "timestamp": "2022-01-03T13:30:00+01:00"
        },
        {
            "username": "Klaus",
            "state": "busy",
            "timestamp": "2022-01-03T13: 30: 00+01: 00"
        },
        {
            "username": "Karina",
            "state": "busy",
            "timestamp": "2022-01-03T13: 30: 00+01: 00"
        },
        {
            "username": "A",
            "state": "das",
            "timestamp": "2022-01-03T13:30:00+01:00"
        }
    ]
}